README.md
setup.py
pytest_fantasy/__init__.py
pytest_fantasy/fixtures.py
pytest_fantasy.egg-info/PKG-INFO
pytest_fantasy.egg-info/SOURCES.txt
pytest_fantasy.egg-info/dependency_links.txt
pytest_fantasy.egg-info/not-zip-safe
pytest_fantasy.egg-info/requires.txt
pytest_fantasy.egg-info/top_level.txt